fatoora/__init__.py
fatoora/_lib.py
fatoora/api.py
fatoora/errors.py
fatoora/libfatoora_ffi.so
fatoora_rs-0.1.0.dist-info/METADATA
fatoora_rs-0.1.0.dist-info/WHEEL
fatoora_rs-0.1.0.dist-info/top_level.txt
fatoora_rs-0.1.0.dist-info/RECORD
