Metadata-Version: 2.4
Name: fatoora-rs
Version: 0.1.0
Summary: Python bindings for the fatoora ZATCA SDK
Author: mqqz
License-Expression: MIT
Project-URL: Homepage, https://github.com/mqqz/fatoora-rs
Project-URL: Repository, https://github.com/mqqz/fatoora-rs
Project-URL: Documentation, https://github.com/mqqz/fatoora-rs
Project-URL: Issues, https://github.com/mqqz/fatoora-rs/issues
Keywords: zatca,invoice,e-invoicing,sdk,ffi
Classifier: Programming Language :: Python :: 3
Classifier: Programming Language :: Python :: 3 :: Only
Classifier: Operating System :: OS Independent
Classifier: Topic :: Software Development :: Libraries
Requires-Python: >=3.9
Requires-Dist: cffi>=1.16
Provides-Extra: dev
Requires-Dist: pytest>=8.0; extra == "dev"
